CHANGELOG.rst
LICENSE.rst
TODO
cidrize.py
cidrize-2.1.0.dist-info/WHEEL
cidrize-2.1.0.dist-info/entry_points.txt
cidrize-2.1.0.dist-info/LICENSE.rst
cidrize-2.1.0.dist-info/METADATA
cidrize-2.1.0.dist-info/RECORD
