Metadata-Version: 2.1
Name: cidrize
Version: 2.1.0
Summary: Cidrize parses IPv4/IPv6 addresses, CIDRs, ranges, and wildcard matches & attempts to return a valid list of IP addresses
Home-page: https://github.com/jathanism/cidrize/
License: BSD-3-Clause
Keywords: Networking,Systems,Administration,IANA,IEEE,CIDR,IP,IPv4,IPv6,IP,Address,Firewalls,Security
Author: Jathan McCollum
Author-email: jathan@gmail.com
Requires-Python: >=3.8,<4.0
Classifier: Development Status :: 5 - Production/Stable
Classifier: Environment :: Console
Classifier: Environment :: Plugins
Classifier: Intended Audience :: Developers
Classifier: Intended Audience :: Education
Classifier: Intended Audience :: Information Technology
Classifier: Intended Audience :: Science/Research
Classifier: Intended Audience :: System Administrators
Classifier: Intended Audience :: Telecommunications Industry
Classifier: License :: OSI Approved :: BSD License
Classifier: Natural Language :: English
Classifier: Operating System :: OS Independent
Classifier: Programming Language :: Python
Classifier: Programming Language :: Python :: 3
Classifier: Programming Language :: Python :: 3.8
Classifier: Programming Language :: Python :: 3.9
Classifier: Programming Language :: Python :: 3.10
Classifier: Programming Language :: Python :: 3.11
Classifier: Programming Language :: Python :: 3 :: Only
Classifier: Topic :: Education :: Testing
Classifier: Topic :: Internet
Classifier: Topic :: Internet :: Name Service (DNS)
Classifier: Topic :: Software Development
Classifier: Topic :: Software Development :: Libraries :: Python Modules
Classifier: Topic :: System :: Networking
Classifier: Topic :: System :: Networking :: Firewalls
Classifier: Topic :: System :: Networking :: Monitoring
Classifier: Topic :: System :: Operating System
Classifier: Topic :: System :: Systems Administration
Classifier: Topic :: Utilities
Requires-Dist: netaddr (>=0.8.0,<0.9.0)
